flask_oidc/__init__.py
flask_oidc/discovery.py
flask_oidc/registration.py
flask_oidc/registration_util.py
tz_flask_oidc-1.4.0.dist-info/LICENSE.txt
tz_flask_oidc-1.4.0.dist-info/METADATA
tz_flask_oidc-1.4.0.dist-info/WHEEL
tz_flask_oidc-1.4.0.dist-info/entry_points.txt
tz_flask_oidc-1.4.0.dist-info/top_level.txt
tz_flask_oidc-1.4.0.dist-info/RECORD
