Metadata-Version: 2.1
Name: tz-flask-oidc
Version: 1.4.0
Summary: OpenID Connect extension for Flask
Home-page: https://github.com/puiterwijk/flask-oidc
Author: Erica Ehrhardt, Patrick Uiterwijk
Author-email: patrick@puiterwijk.org
License: UNKNOWN
Platform: UNKNOWN
Classifier: Environment :: Web Environment
Classifier: Framework :: Flask
Classifier: Intended Audience :: Developers
Classifier: License :: OSI Approved :: BSD License
Classifier: Operating System :: OS Independent
Classifier: Programming Language :: Python
Classifier: Programming Language :: Python :: 2
Classifier: Programming Language :: Python :: 2.6
Classifier: Programming Language :: Python :: 2.7
Classifier: Programming Language :: Python :: 3
Classifier: Programming Language :: Python :: 3.3
Classifier: Programming Language :: Python :: 3.4
Classifier: Topic :: Internet :: WWW/HTTP :: Dynamic Content
Classifier: Topic :: Software Development :: Libraries :: Python Modules
Requires-Dist: Flask
Requires-Dist: itsdangerous
Requires-Dist: oauth2client
Requires-Dist: six
